lynxkit_markdown/__init__.py
lynxkit_markdown/core.py
lynxkit_markdown/fetcher.py
lynxkit_markdown/html_processor.py
lynxkit_markdown-0.1.0.dist-info/licenses/LICENSE
lynxkit_markdown-0.1.0.dist-info/METADATA
lynxkit_markdown-0.1.0.dist-info/WHEEL
lynxkit_markdown-0.1.0.dist-info/top_level.txt
lynxkit_markdown-0.1.0.dist-info/RECORD
