Metadata-Version: 2.4
Name: lynxkit-markdown
Version: 0.1.0
Summary: URLからWebページを取得し、markitdownライブラリを使ってMarkdown形式に変換するシンプルなツール
Author-email: koinunopochi <koinunopochi@gmail.com>
License: MIT
Project-URL: Homepage, https://github.com/koinunopochi/LynxKit-Markdown
Project-URL: Repository, https://github.com/koinunopochi/LynxKit-Markdown
Keywords: markdown,html,converter,url,web,lynxkit,markitdown
Classifier: Development Status :: 3 - Alpha
Classifier: Intended Audience :: Developers
Classifier: License :: OSI Approved :: MIT License
Classifier: Programming Language :: Python :: 3
Classifier: Programming Language :: Python :: 3.8
Classifier: Programming Language :: Python :: 3.9
Classifier: Programming Language :: Python :: 3.10
Classifier: Programming Language :: Python :: 3.11
Classifier: Programming Language :: Python :: 3.12
Classifier: Programming Language :: Python :: 3.13
Classifier: Topic :: Text Processing :: Markup :: Markdown
Classifier: Topic :: Internet :: WWW/HTTP
Classifier: Operating System :: OS Independent
Requires-Python: >=3.8
License-File: LICENSE
Requires-Dist: requests>=2.25.0
Requires-Dist: markitdown>=0.1.1
Dynamic: license-file
